LICENSE
MANIFEST.in
README.md
setup.py
django_theherk_menu_icons.egg-info/PKG-INFO
django_theherk_menu_icons.egg-info/SOURCES.txt
django_theherk_menu_icons.egg-info/dependency_links.txt
django_theherk_menu_icons.egg-info/requires.txt
django_theherk_menu_icons.egg-info/top_level.txt
menu_icons/__init__.py
menu_icons/admin.py
menu_icons/cms_menus.py
menu_icons/cms_toolbars.py
menu_icons/models.py
menu_icons/migrations/0001_initial.py
menu_icons/migrations/__init__.py
menu_icons/templates/menu/top-menu.html