Metadata-Version: 1.1
Name: django-theherk-menu-icons
Version: 2.0.1
Summary: Django CMS navigation modifier to attach icons to menus.
Home-page: https://github.com/theherk/django-theherk-menu-icons
Author: Adam Sherwood
Author-email: theherk@gmail.com
License: see file LICENSE
Download-URL: https://github.com/theherk/django-theherk-menu-icons/archive/2.0.1.zip
Platform: UNKNOWN
Classifier: Environment :: Web Environment
Classifier: Framework :: Django
Classifier: Intended Audience :: Developers
Classifier: Operating System :: OS Independent
Classifier: Programming Language :: Python
Classifier: Programming Language :: Python :: 2.7
Classifier: Programming Language :: Python :: 3.4
Classifier: Topic :: Internet :: WWW/HTTP
Classifier: Topic :: Internet :: WWW/HTTP :: Dynamic Content
